cryptoprice.py
Cryptoprice-0.1.dist-info/DESCRIPTION.rst
Cryptoprice-0.1.dist-info/METADATA
Cryptoprice-0.1.dist-info/RECORD
Cryptoprice-0.1.dist-info/WHEEL
Cryptoprice-0.1.dist-info/entry_points.txt
Cryptoprice-0.1.dist-info/metadata.json
Cryptoprice-0.1.dist-info/top_level.txt
