Metadata-Version: 2.0
Name: Cryptoprice
Version: 0.1
Summary: A CLI to monitor the crypto market and your portfolio.
Home-page: https://github.com/vi-v/cryptoprice
Author: Vishnu Vijayan
Author-email: slpxatwon@gmail.com
License: MIT
Keywords: crypto portfolio cli cryptocurrency market
Platform: UNKNOWN
Classifier: Development Status :: 3 - Alpha
Classifier: Intended Audience :: End Users/Desktop
Classifier: License :: OSI Approved :: MIT License
Requires-Dist: Click
Requires-Dist: requests
Requires-Dist: terminaltables
Requires-Dist: tinydb
Requires-Dist: prompt-toolkit
